grpc_framework/__init__.py
grpc_framework/apps.py
grpc_framework/decorators.py
grpc_framework/exceptions.py
grpc_framework/models.py
grpc_framework/request.py
grpc_framework/response.py
grpc_framework/serializers.py
grpc_framework/server.py
grpc_framework/service.py
grpc_framework/settings.py
grpc_framework/signals.py
grpc_framework/urls.py
grpc_framework/views.py
grpc_framework/grpc_app_template/__init__.py-tpl
grpc_framework/grpc_app_template/app_name.proto
grpc_framework/grpc_app_template/client.py-tpl
grpc_framework/grpc_app_template/service.py-tpl
grpc_framework/grpc_app_template/tests.py-tpl
grpc_framework/interceptors/header.py
grpc_framework/interceptors/log.py
grpc_framework/management/__init__.py
grpc_framework/management/commands/__init__.py
grpc_framework/management/commands/grpcgenerate.py
grpc_framework/management/commands/grpcrunserver.py
grpc_framework/management/commands/grpcstartapp.py
grpc_framework/static/css/grpc_framework.css
grpc_framework/static/js/grpc_framework.js
grpc_framework/templates/grpc_framework/base.html
grpc_framework/utils/__init__.py
grpc_framework/utils/credentials.py
grpc_framework/utils/log.py
grpc_framework/utils/tools.py
django_grpc_framework-0.3.0.dist-info/AUTHORS.rst
django_grpc_framework-0.3.0.dist-info/LICENSE
django_grpc_framework-0.3.0.dist-info/METADATA
django_grpc_framework-0.3.0.dist-info/WHEEL
django_grpc_framework-0.3.0.dist-info/top_level.txt
django_grpc_framework-0.3.0.dist-info/RECORD
