Metadata-Version: 2.1
Name: django-grpc-framework
Version: 0.3.0
Summary: gRPC for Django
Home-page: https://github.com/itswcg/django-grpc-framework
Author: itswcg
Author-email: itswcg@gmail.com
License: Apache Software License 2.0
Keywords: django-grpc-framework
Platform: UNKNOWN
Classifier: Development Status :: 3 - Alpha
Classifier: Framework :: Django :: 1.11
Classifier: Framework :: Django :: 2.1
Classifier: Intended Audience :: Developers
Classifier: License :: OSI Approved :: BSD License
Classifier: Natural Language :: English
Classifier: Programming Language :: Python :: 2
Classifier: Programming Language :: Python :: 2.7
Classifier: Programming Language :: Python :: 3
Classifier: Programming Language :: Python :: 3.5
Classifier: Programming Language :: Python :: 3.6
Requires-Dist: django (>=2.1)
Requires-Dist: grpcio (==1.27.1)
Requires-Dist: grpcio-tools (==1.27.1)
